mcp_caiyun_weather/__init__.py
mcp_caiyun_weather/server.py
mcp_caiyun_weather-0.1.1.dist-info/METADATA
mcp_caiyun_weather-0.1.1.dist-info/WHEEL
mcp_caiyun_weather-0.1.1.dist-info/entry_points.txt
mcp_caiyun_weather-0.1.1.dist-info/licenses/LICENSE
mcp_caiyun_weather-0.1.1.dist-info/RECORD
