Metadata-Version: 2.4
Name: mcp-caiyun-weather
Version: 0.1.1
Summary: Caiyun Weather MCP Server
Project-URL: Homepage, https://github.com/caiyunapp/mcp-caiyun-weather
Project-URL: Issues, https://github.com/caiyunapp/mcp-caiyun-weather/issues
Author-email: adamwen <adamwen829@gmail.com>, tssujt <xujiawei@caiyunapp.com>, caiyunapp <oss@caiyunapp.com>
Maintainer-email: adamwen <adamwen829@gmail.com>, tssujt <xujiawei@caiyunapp.com>, caiyunapp <oss@caiyunapp.com>
License: MIT License
License-File: LICENSE
Keywords: MCP,Weather
Requires-Python: >=3.12
Requires-Dist: httpx>=0.28.1
Requires-Dist: mcp[cli]>=1.5.0
Requires-Dist: pydantic>=2.10.6
